{"imported":false,"data":[{"door_type":"double","door_unlock_sound":"door_metal.ogg","camera":false,"items":[],"default_state":true,"state":true,"secret":false,"perms":{"ace":[],"job":[{"grade":0,"name":"police"}],"discord":[],"identifier":[],"items":[]},"unique_id":"3UFE-MSWV-UUR2-91VR","door_name":"Left Doors","door_data":[{"unique_id":"qrx8Jy4r9mWBtTwe1Zw6Y","model_hash":1591748701,"door_coords":{"z":14.97679805755615,"y":-924.4451293945313,"x":782.8518676757813}},{"unique_id":"e5OOwWmv3oxIh53RG0q7t","model_hash":8891428,"door_coords":{"z":14.97679805755615,"y":-924.4451293945313,"x":781.5443115234375}}],"distance":2,"keep_open":false,"lockpickable":false,"location_group":"Murrieta Heights Large Warehouse","door_sound":"door_metal.ogg"},{"door_type":"double","door_unlock_sound":"door_metal.ogg","camera":false,"items":[],"default_state":true,"state":true,"secret":false,"perms":{"ace":[],"job":[{"grade":0,"name":"police"}],"discord":[],"identifier":[],"items":[]},"unique_id":"7JP1-QFWP-RV9L-JNRQ","door_name":"Right Doors","door_data":[{"unique_id":"fcHRV1gwbfquUxHsxbAGN","model_hash":8891428,"door_coords":{"z":14.97679805755615,"y":-924.4451293945313,"x":796.806396484375}},{"unique_id":"I2yCtI0v7twzEcjOITlyv","model_hash":1591748701,"door_coords":{"z":14.97679805755615,"y":-924.4451293945313,"x":798.1139526367188}}],"distance":2,"keep_open":false,"lockpickable":false,"location_group":"Murrieta Heights Large Warehouse","door_sound":"door_metal.ogg"},{"door_type":"single","door_unlock_sound":"door_metal.ogg","camera":false,"items":[],"default_state":true,"state":true,"secret":false,"perms":{"ace":[],"job":[{"grade":0,"name":"police"}],"discord":[],"identifier":[],"items":[]},"unique_id":"AE4K-N9XF-6CV8-KUEU","door_name":"Office","door_data":[{"unique_id":"qFy9nHvH0rN-3nuoAd42N","model_hash":97276813,"door_coords":{"z":13.88695526123046,"y":-935.7002563476564,"x":807.5770263671875}}],"distance":2,"keep_open":false,"lockpickable":false,"location_group":"Murrieta Heights Large Warehouse","door_sound":"door_metal.ogg"},{"door_type":"garage","door_unlock_sound":"door_metal.ogg","camera":false,"items":[],"default_state":true,"state":true,"secret":false,"perms":{"ace":[],"job":[{"grade":0,"name":"police"}],"discord":[],"identifier":[],"items":[]},"unique_id":"JYU1-RO4Z-7910-BZW1","door_name":"Main Entrance","door_data":[{"unique_id":"IE3i8R_15_3EEmOWw0c_u","model_hash":-73517283,"door_coords":{"z":29.52814292907715,"y":-951.3085327148438,"x":843.4856567382813}}],"distance":10,"keep_open":false,"lockpickable":false,"location_group":"Murrieta Heights Large Warehouse","door_sound":"door_metal.ogg"}],"name":"[GN_Studios]_Murrieta_Heights_Large_Warehouse.json"}