{"data":[{"distance":2,"unique_id":"0BY4-H0AG-5LSR-6ZU2","location_group":"Von Crastenburg Del Perro","door_name":"305","door_sound":"door_regular.ogg","door_data":[{"door_coords":{"x":-1513.91357421875,"z":52.7308120727539,"y":-520.2897338867188},"unique_id":"ThDz5XPvndQbKX73tkbQf","model_hash":2011001180}],"door_unlock_sound":"door_click.ogg","lockpickable":false,"default_state":false,"perms":{"identifier":[],"items":[],"ace":[],"job":[{"name":"police","grade":0}],"discord":[]},"items":[],"keep_open":false,"camera":false,"state":false,"door_type":"single","secret":false},{"distance":2,"unique_id":"0KZE-XP1L-GV9A-OMQD","location_group":"Von Crastenburg Del Perro","door_name":"501","door_sound":"door_regular.ogg","door_data":[{"door_coords":{"x":-1536.4189453125,"z":62.26836776733398,"y":-530.23779296875},"unique_id":"DfEuNHomfZqxoZl3Wpa4O","model_hash":2011001180}],"door_unlock_sound":"door_click.ogg","lockpickable":false,"default_state":false,"perms":{"identifier":[],"items":[],"ace":[],"job":[{"name":"police","grade":0}],"discord":[]},"items":[],"keep_open":false,"camera":false,"state":false,"door_type":"single","secret":false},{"distance":2,"unique_id":"23GF-9B88-W62C-YBA8","location_group":"Von Crastenburg Del Perro","door_name":"204","door_sound":"door_regular.ogg","door_data":[{"door_coords":{"x":-1523.1240234375,"z":47.96160507202148,"y":-526.2798461914063},"unique_id":"LFNz9D-sS3IIF5-Inozd5","model_hash":2011001180}],"door_unlock_sound":"door_click.ogg","lockpickable":false,"default_state":false,"perms":{"identifier":[],"items":[],"ace":[],"job":[{"name":"police","grade":0}],"discord":[]},"items":[],"keep_open":false,"camera":false,"state":false,"door_type":"single","secret":false},{"distance":2,"unique_id":"2YU6-GWD3-VBI2-28HR","location_group":"Von Crastenburg Del Perro","door_name":"502","door_sound":"door_regular.ogg","door_data":[{"door_coords":{"x":-1532.3240966796876,"z":62.26849746704101,"y":-532.26123046875},"unique_id":"n3J8ywRatBZSnBytO23GM","model_hash":2011001180}],"door_unlock_sound":"door_click.ogg","lockpickable":false,"default_state":false,"perms":{"identifier":[],"items":[],"ace":[],"job":[{"name":"police","grade":0}],"discord":[]},"items":[],"keep_open":false,"camera":false,"state":false,"door_type":"single","secret":false},{"distance":2,"unique_id":"3G48-ZHE3-7DAC-YL56","location_group":"Von Crastenburg Del Perro","door_name":"205","door_sound":"door_regular.ogg","door_data":[{"door_coords":{"x":-1513.91357421875,"z":47.96181106567383,"y":-520.2907104492188},"unique_id":"3MyQkWzsmMcp_Oq3DterL","model_hash":2011001180}],"door_unlock_sound":"door_click.ogg","lockpickable":false,"default_state":false,"perms":{"identifier":[],"items":[],"ace":[],"job":[{"name":"police","grade":0}],"discord":[]},"items":[],"keep_open":false,"camera":false,"state":false,"door_type":"single","secret":false},{"distance":2,"unique_id":"4D6R-OJ1E-UFFA-36R2","location_group":"Von Crastenburg Del Perro","door_name":"303","door_sound":"door_regular.ogg","door_data":[{"door_coords":{"x":-1527.21875,"z":52.73047637939453,"y":-524.2553100585938},"unique_id":"oHNuIfBnZ7NpXMA0ckTol","model_hash":2011001180}],"door_unlock_sound":"door_click.ogg","lockpickable":false,"default_state":false,"perms":{"identifier":[],"items":[],"ace":[],"job":[{"name":"police","grade":0}],"discord":[]},"items":[],"keep_open":false,"camera":false,"state":false,"door_type":"single","secret":false},{"distance":2,"unique_id":"5DBV-M1VS-766F-ZAUE","location_group":"Von Crastenburg Del Perro","door_name":"603","door_sound":"door_regular.ogg","door_data":[{"door_coords":{"x":-1527.21875,"z":67.03707122802735,"y":-524.2553100585938},"unique_id":"9m8UkpKpqiLeXmoGwKP9E","model_hash":2011001180}],"door_unlock_sound":"door_click.ogg","lockpickable":false,"default_state":false,"perms":{"identifier":[],"items":[],"ace":[],"job":[{"name":"police","grade":0}],"discord":[]},"items":[],"keep_open":false,"camera":false,"state":false,"door_type":"single","secret":false},{"distance":2,"unique_id":"5OJZ-KG3U-ZURS-C1WG","location_group":"Von Crastenburg Del Perro","door_name":"105","door_sound":"door_regular.ogg","door_data":[{"door_coords":{"x":-1513.91357421875,"z":43.19321060180664,"y":-520.2907104492188},"unique_id":"Y6okZFAEgiIuVEyQwPAzY","model_hash":2011001180}],"door_unlock_sound":"door_click.ogg","lockpickable":false,"default_state":false,"perms":{"identifier":[],"items":[],"ace":[],"job":[{"name":"police","grade":0}],"discord":[]},"items":[],"keep_open":false,"camera":false,"state":false,"door_type":"single","secret":false},{"distance":2,"unique_id":"5UZZ-ONEX-LALM-86H9","location_group":"Von Crastenburg Del Perro","door_name":"404","door_sound":"door_regular.ogg","door_data":[{"door_coords":{"x":-1523.1240234375,"z":57.49970626831055,"y":-526.2788696289063},"unique_id":"Z3INORlRMn_EgHpytOgQQ","model_hash":2011001180}],"door_unlock_sound":"door_click.ogg","lockpickable":false,"default_state":false,"perms":{"identifier":[],"items":[],"ace":[],"job":[{"name":"police","grade":0}],"discord":[]},"items":[],"keep_open":false,"camera":false,"state":false,"door_type":"single","secret":false},{"distance":2,"unique_id":"6OCI-HUCR-UGST-NX0K","location_group":"Von Crastenburg Del Perro","door_name":"504","door_sound":"door_regular.ogg","door_data":[{"door_coords":{"x":-1523.1240234375,"z":62.26870346069336,"y":-526.2788696289063},"unique_id":"NDQ4e5ocfeirTA5wWkvnL","model_hash":2011001180}],"door_unlock_sound":"door_click.ogg","lockpickable":false,"default_state":false,"perms":{"identifier":[],"items":[],"ace":[],"job":[{"name":"police","grade":0}],"discord":[]},"items":[],"keep_open":false,"camera":false,"state":false,"door_type":"single","secret":false},{"distance":2,"unique_id":"78P5-C8N0-GRHK-9OHU","location_group":"Von Crastenburg Del Perro","door_name":"104","door_sound":"door_regular.ogg","door_data":[{"door_coords":{"x":-1523.1240234375,"z":43.1930046081543,"y":-526.2798461914063},"unique_id":"b90Qfl0_7wzsDskm5WGMT","model_hash":2011001180}],"door_unlock_sound":"door_click.ogg","lockpickable":false,"default_state":false,"perms":{"identifier":[],"items":[],"ace":[],"job":[{"name":"police","grade":0}],"discord":[]},"items":[],"keep_open":false,"camera":false,"state":false,"door_type":"single","secret":false},{"distance":2,"unique_id":"C04K-V9YX-PIR3-P2NH","location_group":"Von Crastenburg Del Perro","door_name":"102","door_sound":"door_regular.ogg","door_data":[{"door_coords":{"x":-1532.3240966796876,"z":43.19279861450195,"y":-532.26220703125},"unique_id":"4YQYGfJfn4LpmpB07njgp","model_hash":2011001180}],"door_unlock_sound":"door_click.ogg","lockpickable":false,"default_state":false,"perms":{"identifier":[],"items":[],"ace":[],"job":[{"name":"police","grade":0}],"discord":[]},"items":[],"keep_open":false,"camera":false,"state":false,"door_type":"single","secret":false},{"distance":2,"unique_id":"DVV3-7S65-H6HS-MPFR","location_group":"Von Crastenburg Del Perro","door_name":"503","door_sound":"door_regular.ogg","door_data":[{"door_coords":{"x":-1527.21875,"z":62.26857376098633,"y":-524.2553100585938},"unique_id":"qYDu-HYBQKLtjwfOA5wio","model_hash":2011001180}],"door_unlock_sound":"door_click.ogg","lockpickable":false,"default_state":false,"perms":{"identifier":[],"items":[],"ace":[],"job":[{"name":"police","grade":0}],"discord":[]},"items":[],"keep_open":false,"camera":false,"state":false,"door_type":"single","secret":false},{"distance":2,"unique_id":"ETSA-S6JN-YNN5-Z4DY","location_group":"Von Crastenburg Del Perro","door_name":"405","door_sound":"door_regular.ogg","door_data":[{"door_coords":{"x":-1513.91357421875,"z":57.49991226196289,"y":-520.2897338867188},"unique_id":"SSKkLUlbCw2gpXhtoPCmN","model_hash":2011001180}],"door_unlock_sound":"door_click.ogg","lockpickable":false,"default_state":false,"perms":{"identifier":[],"items":[],"ace":[],"job":[{"name":"police","grade":0}],"discord":[]},"items":[],"keep_open":false,"camera":false,"state":false,"door_type":"single","secret":false},{"distance":2,"unique_id":"G67U-6NMV-KXLR-2QDU","location_group":"Von Crastenburg Del Perro","door_name":"Entrance 2","door_sound":"door_regular.ogg","door_data":[{"door_coords":{"x":-1545.186767578125,"z":36.4009895324707,"y":-530.9111938476563},"unique_id":"VS-0JqefIXq5QYoBnScKW","model_hash":-1200705506},{"door_coords":{"x":-1545.9774169921876,"z":36.40097045898437,"y":-531.4258422851563},"unique_id":"jWqwoSTYWuh7-OpxTEECQ","model_hash":1961273627}],"door_unlock_sound":"door_click.ogg","lockpickable":false,"default_state":false,"perms":{"identifier":[],"items":[],"ace":[],"job":[{"name":"police","grade":0}],"discord":[]},"items":[],"keep_open":false,"camera":false,"state":false,"door_type":"double","secret":false},{"distance":2,"unique_id":"HTOT-Y04Q-WP8L-MPDB","location_group":"Von Crastenburg Del Perro","door_name":"103","door_sound":"door_regular.ogg","door_data":[{"door_coords":{"x":-1527.21875,"z":43.19287490844726,"y":-524.2562866210938},"unique_id":"E3eGS11mk2imS54u_-rHv","model_hash":2011001180}],"door_unlock_sound":"door_click.ogg","lockpickable":false,"default_state":false,"perms":{"identifier":[],"items":[],"ace":[],"job":[{"name":"police","grade":0}],"discord":[]},"items":[],"keep_open":false,"camera":false,"state":false,"door_type":"single","secret":false},{"distance":2,"unique_id":"HWGX-AEQ9-HJHP-IPK0","location_group":"Von Crastenburg Del Perro","door_name":"203","door_sound":"door_regular.ogg","door_data":[{"door_coords":{"x":-1527.21875,"z":47.96147537231445,"y":-524.2562866210938},"unique_id":"uDcLjaUevczfMZoTvgiTO","model_hash":2011001180}],"door_unlock_sound":"door_click.ogg","lockpickable":false,"default_state":false,"perms":{"identifier":[],"items":[],"ace":[],"job":[{"name":"police","grade":0}],"discord":[]},"items":[],"keep_open":false,"camera":false,"state":false,"door_type":"single","secret":false},{"distance":2,"unique_id":"KBVF-L9Y4-N0C4-EMWR","location_group":"Von Crastenburg Del Perro","door_name":"402","door_sound":"door_regular.ogg","door_data":[{"door_coords":{"x":-1532.3240966796876,"z":57.4995002746582,"y":-532.26123046875},"unique_id":"9iWN5yvQT1ktTgf4m978U","model_hash":2011001180}],"door_unlock_sound":"door_click.ogg","lockpickable":false,"default_state":false,"perms":{"identifier":[],"items":[],"ace":[],"job":[{"name":"police","grade":0}],"discord":[]},"items":[],"keep_open":false,"camera":false,"state":false,"door_type":"single","secret":false},{"distance":2,"unique_id":"KH35-MWD7-C6JC-RRU8","location_group":"Von Crastenburg Del Perro","door_name":"302","door_sound":"door_regular.ogg","door_data":[{"door_coords":{"x":-1532.3240966796876,"z":52.73040008544922,"y":-532.26123046875},"unique_id":"VeBV7FKIIWFyqbQ90S68o","model_hash":2011001180}],"door_unlock_sound":"door_click.ogg","lockpickable":false,"default_state":false,"perms":{"identifier":[],"items":[],"ace":[],"job":[{"name":"police","grade":0}],"discord":[]},"items":[],"keep_open":false,"camera":false,"state":false,"door_type":"single","secret":false},{"distance":2,"unique_id":"LHXU-NLJ0-VJE1-M632","location_group":"Von Crastenburg Del Perro","door_name":"101","door_sound":"door_regular.ogg","door_data":[{"door_coords":{"x":-1536.4189453125,"z":43.19266891479492,"y":-530.23876953125},"unique_id":"sUAvF8AAUFUj6wi49JX9m","model_hash":2011001180}],"door_unlock_sound":"door_click.ogg","lockpickable":false,"default_state":false,"perms":{"identifier":[],"items":[],"ace":[],"job":[{"name":"police","grade":0}],"discord":[]},"items":[],"keep_open":false,"camera":false,"state":false,"door_type":"single","secret":false},{"distance":2,"unique_id":"PC59-FI91-0OJ6-0IZN","location_group":"Von Crastenburg Del Perro","door_name":"201","door_sound":"door_regular.ogg","door_data":[{"door_coords":{"x":-1536.4189453125,"z":47.96126937866211,"y":-530.23876953125},"unique_id":"OatWwPO28JW2W-17eSiTq","model_hash":2011001180}],"door_unlock_sound":"door_click.ogg","lockpickable":false,"default_state":false,"perms":{"identifier":[],"items":[],"ace":[],"job":[{"name":"police","grade":0}],"discord":[]},"items":[],"keep_open":false,"camera":false,"state":false,"door_type":"single","secret":false},{"distance":2,"unique_id":"PI4Y-J5LH-0JSY-67DK","location_group":"Von Crastenburg Del Perro","door_name":"202","door_sound":"door_regular.ogg","door_data":[{"door_coords":{"x":-1532.3240966796876,"z":47.96139907836914,"y":-532.26220703125},"unique_id":"43u5vJ6-3nZY9VcivQH3h","model_hash":2011001180}],"door_unlock_sound":"door_click.ogg","lockpickable":false,"default_state":false,"perms":{"identifier":[],"items":[],"ace":[],"job":[{"name":"police","grade":0}],"discord":[]},"items":[],"keep_open":false,"camera":false,"state":false,"door_type":"single","secret":false},{"distance":2,"unique_id":"Q4H7-17V6-KVB2-3G0E","location_group":"Von Crastenburg Del Perro","door_name":"304","door_sound":"door_regular.ogg","door_data":[{"door_coords":{"x":-1523.1240234375,"z":52.73060607910156,"y":-526.2788696289063},"unique_id":"ODvtTpB0n8Hfj4rgnnniC","model_hash":2011001180}],"door_unlock_sound":"door_click.ogg","lockpickable":false,"default_state":false,"perms":{"identifier":[],"items":[],"ace":[],"job":[{"name":"police","grade":0}],"discord":[]},"items":[],"keep_open":false,"camera":false,"state":false,"door_type":"single","secret":false},{"distance":10,"unique_id":"R5GQ-QXF6-TKEP-20XP","location_group":"Von Crastenburg Del Perro","door_name":"Garage","door_sound":"door_switch.ogg","door_data":[{"door_coords":{"x":-1512.430908203125,"z":37.51992034912109,"y":-516.2996215820313},"unique_id":"XpMOo8WZ4IxOcjHJcHksH","model_hash":-1656607252}],"door_unlock_sound":"door_switch.ogg","lockpickable":false,"default_state":false,"perms":{"identifier":[],"items":[],"ace":[],"job":[{"name":"police","grade":0}],"discord":[]},"items":[],"keep_open":false,"camera":false,"state":false,"door_type":"garage","secret":false},{"distance":2,"unique_id":"RFG1-QDWE-D3GF-LQ09","location_group":"Von Crastenburg Del Perro","door_name":"Entrance 1","door_sound":"door_regular.ogg","door_data":[{"door_coords":{"x":-1543.5126953125,"z":36.40102386474609,"y":-529.8226318359375},"unique_id":"L6QKAgFrxv9kKLcgE-aRA","model_hash":-1200705506},{"door_coords":{"x":-1544.303466796875,"z":36.40100860595703,"y":-530.3372802734375},"unique_id":"VDEc5YCYW9oxfZdBvlcmL","model_hash":1961273627}],"door_unlock_sound":"door_click.ogg","lockpickable":false,"default_state":false,"perms":{"identifier":[],"items":[],"ace":[],"job":[{"name":"police","grade":0}],"discord":[]},"items":[],"keep_open":false,"camera":false,"state":false,"door_type":"double","secret":false},{"distance":2,"unique_id":"SFV3-7M0Q-B2S8-CX3Z","location_group":"Von Crastenburg Del Perro","door_name":"403","door_sound":"door_regular.ogg","door_data":[{"door_coords":{"x":-1527.21875,"z":57.49957656860351,"y":-524.2553100585938},"unique_id":"MIDSYRZnTv0xNvVD4u3bY","model_hash":2011001180}],"door_unlock_sound":"door_click.ogg","lockpickable":false,"default_state":false,"perms":{"identifier":[],"items":[],"ace":[],"job":[{"name":"police","grade":0}],"discord":[]},"items":[],"keep_open":false,"camera":false,"state":false,"door_type":"single","secret":false},{"distance":2,"unique_id":"SNZ5-TJ6D-M25L-6I7T","location_group":"Von Crastenburg Del Perro","door_name":"505","door_sound":"door_regular.ogg","door_data":[{"door_coords":{"x":-1513.91357421875,"z":62.2689094543457,"y":-520.2897338867188},"unique_id":"HtQ3BNYVAtKOY57V2_izW","model_hash":2011001180}],"door_unlock_sound":"door_click.ogg","lockpickable":false,"default_state":false,"perms":{"identifier":[],"items":[],"ace":[],"job":[{"name":"police","grade":0}],"discord":[]},"items":[],"keep_open":false,"camera":false,"state":false,"door_type":"single","secret":false},{"distance":2,"unique_id":"SXGM-1USR-4V2J-X0D8","location_group":"Von Crastenburg Del Perro","door_name":"601","door_sound":"door_regular.ogg","door_data":[{"door_coords":{"x":-1536.4189453125,"z":67.03687286376953,"y":-530.23779296875},"unique_id":"TeGiUL7wtsE2zr5bAwv1I","model_hash":2011001180}],"door_unlock_sound":"door_click.ogg","lockpickable":false,"default_state":false,"perms":{"identifier":[],"items":[],"ace":[],"job":[{"name":"police","grade":0}],"discord":[]},"items":[],"keep_open":false,"camera":false,"state":false,"door_type":"single","secret":false},{"distance":2,"unique_id":"U3LS-C5X2-HZGB-VH1I","location_group":"Von Crastenburg Del Perro","door_name":"604","door_sound":"door_regular.ogg","door_data":[{"door_coords":{"x":-1523.1240234375,"z":67.03719329833985,"y":-526.2788696289063},"unique_id":"-cfLQo32of7pAbOAqc5Hj","model_hash":2011001180}],"door_unlock_sound":"door_click.ogg","lockpickable":false,"default_state":false,"perms":{"identifier":[],"items":[],"ace":[],"job":[{"name":"police","grade":0}],"discord":[]},"items":[],"keep_open":false,"camera":false,"state":false,"door_type":"single","secret":false},{"distance":2,"unique_id":"WDSR-HMCU-HPC7-6KE7","location_group":"Von Crastenburg Del Perro","door_name":"605","door_sound":"door_regular.ogg","door_data":[{"door_coords":{"x":-1513.91357421875,"z":67.03739929199219,"y":-520.2897338867188},"unique_id":"MjZFW_7KN3lf_8UUkh-OS","model_hash":2011001180}],"door_unlock_sound":"door_click.ogg","lockpickable":false,"default_state":false,"perms":{"identifier":[],"items":[],"ace":[],"job":[{"name":"police","grade":0}],"discord":[]},"items":[],"keep_open":false,"camera":false,"state":false,"door_type":"single","secret":false},{"distance":2,"unique_id":"YNW0-ASSY-2R18-56Z9","location_group":"Von Crastenburg Del Perro","door_name":"301","door_sound":"door_regular.ogg","door_data":[{"door_coords":{"x":-1536.4189453125,"z":52.73027038574219,"y":-530.23779296875},"unique_id":"_sicphG9U20GiUf_mHy09","model_hash":2011001180}],"door_unlock_sound":"door_click.ogg","lockpickable":false,"default_state":false,"perms":{"identifier":[],"items":[],"ace":[],"job":[{"name":"police","grade":0}],"discord":[]},"items":[],"keep_open":false,"camera":false,"state":false,"door_type":"single","secret":false},{"distance":2,"unique_id":"ZON0-5WR8-SXBG-CW62","location_group":"Von Crastenburg Del Perro","door_name":"401","door_sound":"door_regular.ogg","door_data":[{"door_coords":{"x":-1536.4189453125,"z":57.49937057495117,"y":-530.23779296875},"unique_id":"INR6Af3UkXb0R2gUAjo6O","model_hash":2011001180}],"door_unlock_sound":"door_click.ogg","lockpickable":false,"default_state":false,"perms":{"identifier":[],"items":[],"ace":[],"job":[{"name":"police","grade":0}],"discord":[]},"items":[],"keep_open":false,"camera":false,"state":false,"door_type":"single","secret":false},{"distance":2,"unique_id":"ZQSR-D4F1-JMQ8-YQTH","location_group":"Von Crastenburg Del Perro","door_name":"602","door_sound":"door_regular.ogg","door_data":[{"door_coords":{"x":-1532.3240966796876,"z":67.03699493408203,"y":-532.26123046875},"unique_id":"7AVoofbtbJTVZ7ImWowuq","model_hash":2011001180}],"door_unlock_sound":"door_click.ogg","lockpickable":false,"default_state":false,"perms":{"identifier":[],"items":[],"ace":[],"job":[{"name":"police","grade":0}],"discord":[]},"items":[],"keep_open":false,"camera":false,"state":false,"door_type":"single","secret":false}],"imported":false,"name":"[GN_Studios]_Von_Crastenburg_Del_Perro.json"}