{"imported":false,"data":[{"default_state":false,"door_type":"double","items":[],"door_unlock_sound":"door_click.ogg","distance":2,"state":false,"keep_open":false,"camera":false,"location_group":"FLEECA Morningwood","door_name":"Entrance","door_sound":"door_regular.ogg","door_data":[{"unique_id":"QlGpI64M1ul3kjUesUDJu","door_coords":{"z":38.13204574584961,"y":-327.6455078125,"x":-1213.6524658203126},"pivot_coords":{"z":38.13204574584961,"y":-327.3523864746094,"x":-1213.0738525390626},"model_hash":73386408},{"unique_id":"Vc-cJvohWqY-RnI-8-RmO","door_coords":{"z":38.13210678100586,"y":-328.2337341308594,"x":-1214.8070068359376},"pivot_coords":{"z":38.13210678100586,"y":-328.5237121582031,"x":-1215.38623046875},"model_hash":-1152174184}],"secret":false,"lockpickable":false,"perms":{"job":[{"name":"police","grade":0}],"discord":[],"items":[],"passcode":"","identifier":[],"ace":[]},"unique_id":"KUCQ-IH0H-B42X-X6RO"},{"default_state":false,"door_type":"single","items":[],"door_unlock_sound":"door_click.ogg","distance":2,"state":false,"keep_open":false,"camera":false,"location_group":"FLEECA Morningwood","door_name":"Teller Room","door_sound":"door_regular.ogg","door_data":[{"unique_id":"KreN4FAwphSF6m1TqMrVs","door_coords":{"z":37.86096954345703,"y":-334.2589416503906,"x":-1215.14306640625},"pivot_coords":{"z":38.05551147460937,"y":-334.7280883789063,"x":-1214.9053955078126},"model_hash":-1201894283}],"secret":false,"lockpickable":false,"perms":{"job":[{"name":"police","grade":0}],"discord":[],"items":[],"passcode":"","identifier":[],"ace":[]},"unique_id":"LZ36-LYRG-F800-KHLM"},{"default_state":false,"door_type":"single","items":[],"door_unlock_sound":"door_click.ogg","distance":2,"state":false,"keep_open":false,"camera":false,"location_group":"FLEECA Morningwood","door_name":"Vault","door_sound":"door_regular.ogg","door_data":[{"unique_id":"ZsGxfiHdJZIcXYHRTmO1q","door_coords":{"z":38.03965759277344,"y":-335.1938781738281,"x":-1210.814453125},"pivot_coords":{"z":38.03940963745117,"y":-334.5730895996094,"x":-1211.277587890625},"model_hash":839234948}],"secret":false,"lockpickable":false,"perms":{"job":[{"name":"police","grade":0}],"discord":[],"items":[],"passcode":"","identifier":[],"ace":[]},"unique_id":"8EAF-UO81-769B-V66M"},{"default_state":false,"door_type":"single","items":[],"door_unlock_sound":"door_click.ogg","distance":2,"state":false,"keep_open":false,"camera":false,"location_group":"FLEECA Morningwood","door_name":"Vault 2","door_sound":"door_regular.ogg","door_data":[{"unique_id":"mrCsfUjUy3gw_JvvaFlaB","door_coords":{"z":38.07925415039062,"y":-335.4938049316406,"x":-1208.048583984375},"pivot_coords":{"z":38.07925415039062,"y":-335.1289367675781,"x":-1207.3282470703126},"model_hash":-1591004109}],"secret":false,"lockpickable":false,"perms":{"job":[{"name":"police","grade":0}],"discord":[],"items":[],"passcode":"","identifier":[],"ace":[]},"unique_id":"4Z4G-VHTU-0X9J-FB9X"}],"name":"[K4MB1]_FLEECA_Morningwood.json"}