{"name":"[Kiiya]_La_Puerta_B.json","data":[{"door_data":[{"pivot_coords":{"y":-1029.1903076171876,"z":24.48444557189941,"x":-466.8234558105469},"door_coords":{"y":-1029.190185546875,"z":24.48444557189941,"x":-467.35308837890627},"model_hash":1051762694,"unique_id":"s4v_zzTdKxnW8TMImlu_B"},{"pivot_coords":{"y":-1029.1903076171876,"z":24.48444557189941,"x":-468.9356384277344},"door_coords":{"y":-1029.1904296875,"z":24.48444557189941,"x":-468.406005859375},"model_hash":1051762694,"unique_id":"WY1wPUHacAnIQcWGBCouR"}],"location_group":"La Puerta B","keep_open":false,"secret":false,"items":[],"door_sound":"door_regular.ogg","camera":false,"default_state":false,"door_name":"Entrance 1","door_type":"double","perms":{"ace":[],"passcode":"","identifier":[],"discord":[],"job":[{"name":"police","grade":0}],"items":[]},"unique_id":"C7AC-5HG6-F0M4-RF66","door_unlock_sound":"door_click.ogg","distance":2,"state":false,"lockpickable":false},{"door_data":[{"pivot_coords":{"y":-1029.1903076171876,"z":24.48444557189941,"x":-473.7649841308594},"door_coords":{"y":-1029.190185546875,"z":24.48444557189941,"x":-474.2946166992188},"model_hash":1051762694,"unique_id":"Ds2YdOwb8mr3LlR26EpND"},{"pivot_coords":{"y":-1029.1903076171876,"z":24.48444557189941,"x":-475.8771667480469},"door_coords":{"y":-1029.1904296875,"z":24.48444557189941,"x":-475.3475341796875},"model_hash":1051762694,"unique_id":"j_Ue5DzF48xia3D3xQzUx"}],"location_group":"La Puerta B","keep_open":false,"secret":false,"items":[],"door_sound":"door_regular.ogg","camera":false,"default_state":false,"door_name":"Entrance 2","door_type":"double","perms":{"ace":[],"passcode":"","identifier":[],"discord":[],"job":[{"name":"police","grade":0}],"items":[]},"unique_id":"AZ8P-TJOM-B5GH-HYWP","door_unlock_sound":"door_click.ogg","distance":2,"state":false,"lockpickable":false},{"location_group":"La Puerta B","keep_open":false,"secret":false,"auto_lock":5,"door_name":"100","perms":{"ace":[],"passcode":"","identifier":[],"discord":[],"job":[{"name":"police","grade":0}],"items":[]},"unique_id":"U8C5-CMED-G9GR-AM3W","door_unlock_sound":"door_click.ogg","distance":2,"state":true,"lockpickable":false,"door_data":[{"pivot_coords":{"y":-1041.1383056640626,"z":43.9710693359375,"x":-492.375732421875},"door_coords":{"y":-1041.1383056640626,"z":43.97111892700195,"x":-493.02581787109377},"model_hash":-1028247766,"unique_id":"xuV8LhEv8gCG3gBBk0EgV"}],"camera":false,"door_type":"single","default_state":true,"door_sound":"door_regular.ogg","items":[]},{"location_group":"La Puerta B","keep_open":false,"secret":false,"auto_lock":5,"door_name":"101","perms":{"ace":[],"passcode":"","identifier":[],"discord":[],"job":[{"name":"police","grade":0}],"items":[]},"unique_id":"BQMD-30P4-8ZGX-AOOP","door_unlock_sound":"door_click.ogg","distance":2,"state":true,"lockpickable":false,"door_data":[{"pivot_coords":{"y":-1046.199462890625,"z":43.9710693359375,"x":-478.69244384765627},"door_coords":{"y":-1046.199462890625,"z":43.97111892700195,"x":-478.0423583984375},"model_hash":-1028247766,"unique_id":"TecY6A3FVTkeAB64Gl1e6"}],"camera":false,"door_type":"single","default_state":true,"door_sound":"door_regular.ogg","items":[]},{"location_group":"La Puerta B","keep_open":false,"secret":false,"auto_lock":5,"door_name":"102","perms":{"ace":[],"passcode":"","identifier":[],"discord":[],"job":[{"name":"police","grade":0}],"items":[]},"unique_id":"A9VR-HXDN-XY2C-VPXZ","door_unlock_sound":"door_click.ogg","distance":2,"state":true,"lockpickable":false,"door_data":[{"pivot_coords":{"y":-1041.1383056640626,"z":43.9710693359375,"x":-478.3059692382813},"door_coords":{"y":-1041.1383056640626,"z":43.97111892700195,"x":-478.9560546875},"model_hash":-1028247766,"unique_id":"yAWN-kkm1L2dfYhe_iXzc"}],"camera":false,"door_type":"single","default_state":true,"door_sound":"door_regular.ogg","items":[]},{"location_group":"La Puerta B","keep_open":false,"secret":false,"auto_lock":5,"door_name":"103","perms":{"ace":[],"passcode":"","identifier":[],"discord":[],"job":[{"name":"police","grade":0}],"items":[]},"unique_id":"OF8I-15JW-N7D5-5NIN","door_unlock_sound":"door_click.ogg","distance":2,"state":true,"lockpickable":false,"door_data":[{"pivot_coords":{"y":-1046.199462890625,"z":43.9710693359375,"x":-464.7496337890625},"door_coords":{"y":-1046.199462890625,"z":43.97111892700195,"x":-464.09954833984377},"model_hash":-1028247766,"unique_id":"z0yDsgN-Y_cvr_AOmZsPH"}],"camera":false,"door_type":"single","default_state":true,"door_sound":"door_regular.ogg","items":[]},{"location_group":"La Puerta B","keep_open":false,"secret":false,"auto_lock":5,"door_name":"104","perms":{"ace":[],"passcode":"","identifier":[],"discord":[],"job":[{"name":"police","grade":0}],"items":[]},"unique_id":"OKCT-K6JK-ER5R-CH4I","door_unlock_sound":"door_click.ogg","distance":2,"state":true,"lockpickable":false,"door_data":[{"pivot_coords":{"y":-1041.1383056640626,"z":43.9710693359375,"x":-464.44775390625},"door_coords":{"y":-1041.1383056640626,"z":43.97111892700195,"x":-465.0978393554688},"model_hash":-1028247766,"unique_id":"qfgL4agb03ZR9IBeJDJMq"}],"camera":false,"door_type":"single","default_state":true,"door_sound":"door_regular.ogg","items":[]},{"location_group":"La Puerta B","keep_open":false,"secret":false,"auto_lock":5,"door_name":"105","perms":{"ace":[],"passcode":"","identifier":[],"discord":[],"job":[{"name":"police","grade":0}],"items":[]},"unique_id":"XH4K-MEG2-YSNA-4J9A","door_unlock_sound":"door_click.ogg","distance":2,"state":true,"lockpickable":false,"door_data":[{"pivot_coords":{"y":-1046.199462890625,"z":43.9710693359375,"x":-450.83782958984377},"door_coords":{"y":-1046.199462890625,"z":43.97111892700195,"x":-450.187744140625},"model_hash":-1028247766,"unique_id":"broieUOhSYnuY_2FOW5lJ"}],"camera":false,"door_type":"single","default_state":true,"door_sound":"door_regular.ogg","items":[]},{"location_group":"La Puerta B","keep_open":false,"secret":false,"auto_lock":5,"door_name":"106","perms":{"ace":[],"passcode":"","identifier":[],"discord":[],"job":[{"name":"police","grade":0}],"items":[]},"unique_id":"RR1Z-ROMG-UR8E-IZT3","door_unlock_sound":"door_click.ogg","distance":2,"state":true,"lockpickable":false,"door_data":[{"pivot_coords":{"y":-1041.1383056640626,"z":43.9710693359375,"x":-450.5216674804688},"door_coords":{"y":-1041.1383056640626,"z":43.97111892700195,"x":-451.1717529296875},"model_hash":-1028247766,"unique_id":"o33NStpU3HUkIU0NpC7xl"}],"camera":false,"door_type":"single","default_state":true,"door_sound":"door_regular.ogg","items":[]},{"location_group":"La Puerta B","keep_open":false,"secret":false,"auto_lock":5,"door_name":"200","perms":{"ace":[],"passcode":"","identifier":[],"discord":[],"job":[{"name":"police","grade":0}],"items":[]},"unique_id":"ZLSI-JMM0-PT00-SH6J","door_unlock_sound":"door_click.ogg","distance":2,"state":true,"lockpickable":false,"door_data":[{"pivot_coords":{"y":-1041.1383056640626,"z":54.97110748291015,"x":-492.375732421875},"door_coords":{"y":-1041.1383056640626,"z":54.97115707397461,"x":-493.02581787109377},"model_hash":-1028247766,"unique_id":"tleq8otkNN3yz9daMiYXG"}],"camera":false,"door_type":"single","default_state":true,"door_sound":"door_regular.ogg","items":[]},{"location_group":"La Puerta B","keep_open":false,"secret":false,"auto_lock":5,"door_name":"201","perms":{"ace":[],"passcode":"","identifier":[],"discord":[],"job":[{"name":"police","grade":0}],"items":[]},"unique_id":"F1ER-RUWK-PLS2-S6HJ","door_unlock_sound":"door_click.ogg","distance":2,"state":true,"lockpickable":false,"door_data":[{"pivot_coords":{"y":-1046.199462890625,"z":54.97110748291015,"x":-478.69244384765627},"door_coords":{"y":-1046.199462890625,"z":54.97115707397461,"x":-478.0423583984375},"model_hash":-1028247766,"unique_id":"rGac2ph2_05ER1xU6Hd5C"}],"camera":false,"door_type":"single","default_state":true,"door_sound":"door_regular.ogg","items":[]},{"location_group":"La Puerta B","keep_open":false,"secret":false,"auto_lock":5,"door_name":"202","perms":{"ace":[],"passcode":"","identifier":[],"discord":[],"job":[{"name":"police","grade":0}],"items":[]},"unique_id":"O12W-ESSR-4E7Z-ZOO8","door_unlock_sound":"door_click.ogg","distance":2,"state":true,"lockpickable":false,"door_data":[{"pivot_coords":{"y":-1041.1383056640626,"z":54.97110748291015,"x":-478.3059692382813},"door_coords":{"y":-1041.1383056640626,"z":54.97115707397461,"x":-478.9560546875},"model_hash":-1028247766,"unique_id":"AN9hzCQYwHzz9juNp1pNW"}],"camera":false,"door_type":"single","default_state":true,"door_sound":"door_regular.ogg","items":[]},{"location_group":"La Puerta B","keep_open":false,"secret":false,"auto_lock":5,"door_name":"203","perms":{"ace":[],"passcode":"","identifier":[],"discord":[],"job":[{"name":"police","grade":0}],"items":[]},"unique_id":"SRM2-NST0-LVX0-B1QE","door_unlock_sound":"door_click.ogg","distance":2,"state":true,"lockpickable":false,"door_data":[{"pivot_coords":{"y":-1046.199462890625,"z":54.97110748291015,"x":-464.7496337890625},"door_coords":{"y":-1046.199462890625,"z":54.97115707397461,"x":-464.09954833984377},"model_hash":-1028247766,"unique_id":"Ail99hwzGULVxQ0Tk5e8p"}],"camera":false,"door_type":"single","default_state":true,"door_sound":"door_regular.ogg","items":[]},{"location_group":"La Puerta B","keep_open":false,"secret":false,"auto_lock":5,"door_name":"204","perms":{"ace":[],"passcode":"","identifier":[],"discord":[],"job":[{"name":"police","grade":0}],"items":[]},"unique_id":"P8WZ-2C6H-V5OV-HY7I","door_unlock_sound":"door_click.ogg","distance":2,"state":true,"lockpickable":false,"door_data":[{"pivot_coords":{"y":-1041.1383056640626,"z":54.97110748291015,"x":-464.44775390625},"door_coords":{"y":-1041.1383056640626,"z":54.97115707397461,"x":-465.0978393554688},"model_hash":-1028247766,"unique_id":"Ift4gEJnPcph5YCGGjGvG"}],"camera":false,"door_type":"single","default_state":true,"door_sound":"door_regular.ogg","items":[]},{"location_group":"La Puerta B","keep_open":false,"secret":false,"auto_lock":5,"door_name":"205","perms":{"ace":[],"passcode":"","identifier":[],"discord":[],"job":[{"name":"police","grade":0}],"items":[]},"unique_id":"B9UC-NSPI-VQ7B-OYZ6","door_unlock_sound":"door_click.ogg","distance":2,"state":true,"lockpickable":false,"door_data":[{"pivot_coords":{"y":-1046.199462890625,"z":54.97110748291015,"x":-450.83782958984377},"door_coords":{"y":-1046.199462890625,"z":54.97115707397461,"x":-450.187744140625},"model_hash":-1028247766,"unique_id":"txWaB2I-K5sr3emi0Wj8f"}],"camera":false,"door_type":"single","default_state":true,"door_sound":"door_regular.ogg","items":[]},{"location_group":"La Puerta B","keep_open":false,"secret":false,"auto_lock":5,"door_name":"206","perms":{"ace":[],"passcode":"","identifier":[],"discord":[],"job":[{"name":"police","grade":0}],"items":[]},"unique_id":"90JF-V4IH-NXLT-BR0S","door_unlock_sound":"door_click.ogg","distance":2,"state":true,"lockpickable":false,"door_data":[{"pivot_coords":{"y":-1041.1383056640626,"z":54.97110748291015,"x":-450.5216674804688},"door_coords":{"y":-1041.1383056640626,"z":54.97115707397461,"x":-451.1717529296875},"model_hash":-1028247766,"unique_id":"YXNo3EheiIkaWtKbZayqd"}],"camera":false,"door_type":"single","default_state":true,"door_sound":"door_regular.ogg","items":[]},{"location_group":"La Puerta B","keep_open":false,"secret":false,"auto_lock":5,"door_name":"300","perms":{"ace":[],"passcode":"","identifier":[],"discord":[],"job":[{"name":"police","grade":0}],"items":[]},"unique_id":"LICH-CW2B-60NJ-KY0I","door_unlock_sound":"door_click.ogg","distance":2,"state":true,"lockpickable":false,"door_data":[{"pivot_coords":{"y":-1041.1383056640626,"z":65.97110748291016,"x":-492.375732421875},"door_coords":{"y":-1041.1383056640626,"z":65.97115325927735,"x":-493.02581787109377},"model_hash":-1028247766,"unique_id":"6i4OtrP76KFrXwiixIYv1"}],"camera":false,"door_type":"single","default_state":true,"door_sound":"door_regular.ogg","items":[]},{"location_group":"La Puerta B","keep_open":false,"secret":false,"auto_lock":5,"door_name":"301","perms":{"ace":[],"passcode":"","identifier":[],"discord":[],"job":[{"name":"police","grade":0}],"items":[]},"unique_id":"EGXO-6ZFC-02WE-OFAA","door_unlock_sound":"door_click.ogg","distance":2,"state":true,"lockpickable":false,"door_data":[{"pivot_coords":{"y":-1046.199462890625,"z":65.97110748291016,"x":-478.69244384765627},"door_coords":{"y":-1046.199462890625,"z":65.97115325927735,"x":-478.0423583984375},"model_hash":-1028247766,"unique_id":"cgG8MPxozhOunfUppZwFZ"}],"camera":false,"door_type":"single","default_state":true,"door_sound":"door_regular.ogg","items":[]},{"location_group":"La Puerta B","keep_open":false,"secret":false,"auto_lock":5,"door_name":"302","perms":{"ace":[],"passcode":"","identifier":[],"discord":[],"job":[{"name":"police","grade":0}],"items":[]},"unique_id":"UC14-YENZ-YZ1P-OF5R","door_unlock_sound":"door_click.ogg","distance":2,"state":true,"lockpickable":false,"door_data":[{"pivot_coords":{"y":-1041.1383056640626,"z":65.97110748291016,"x":-478.3059692382813},"door_coords":{"y":-1041.1383056640626,"z":65.97115325927735,"x":-478.9560546875},"model_hash":-1028247766,"unique_id":"Kg2-Ok6kXYCql0jLPaw1i"}],"camera":false,"door_type":"single","default_state":true,"door_sound":"door_regular.ogg","items":[]},{"location_group":"La Puerta B","keep_open":false,"secret":false,"auto_lock":5,"door_name":"303","perms":{"ace":[],"passcode":"","identifier":[],"discord":[],"job":[{"name":"police","grade":0}],"items":[]},"unique_id":"ZLH9-QVBN-VTG3-64KL","door_unlock_sound":"door_click.ogg","distance":2,"state":true,"lockpickable":false,"door_data":[{"pivot_coords":{"y":-1046.199462890625,"z":65.97110748291016,"x":-464.7496337890625},"door_coords":{"y":-1046.199462890625,"z":65.97115325927735,"x":-464.09954833984377},"model_hash":-1028247766,"unique_id":"58xejKiBllSzTaccKdzp0"}],"camera":false,"door_type":"single","default_state":true,"door_sound":"door_regular.ogg","items":[]},{"location_group":"La Puerta B","keep_open":false,"secret":false,"auto_lock":5,"door_name":"304","perms":{"ace":[],"passcode":"","identifier":[],"discord":[],"job":[{"name":"police","grade":0}],"items":[]},"unique_id":"0YUH-WN8C-G022-OSRW","door_unlock_sound":"door_click.ogg","distance":2,"state":true,"lockpickable":false,"door_data":[{"pivot_coords":{"y":-1041.1383056640626,"z":65.97110748291016,"x":-464.44775390625},"door_coords":{"y":-1041.1383056640626,"z":65.97115325927735,"x":-465.0978393554688},"model_hash":-1028247766,"unique_id":"T6WXOocpCO5qY-mnONf9F"}],"camera":false,"door_type":"single","default_state":true,"door_sound":"door_regular.ogg","items":[]},{"location_group":"La Puerta B","keep_open":false,"secret":false,"auto_lock":5,"door_name":"305","perms":{"ace":[],"passcode":"","identifier":[],"discord":[],"job":[{"name":"police","grade":0}],"items":[]},"unique_id":"C4PA-DCBY-XX2A-91F3","door_unlock_sound":"door_click.ogg","distance":2,"state":true,"lockpickable":false,"door_data":[{"pivot_coords":{"y":-1046.199462890625,"z":65.97110748291016,"x":-450.83782958984377},"door_coords":{"y":-1046.199462890625,"z":65.97115325927735,"x":-450.187744140625},"model_hash":-1028247766,"unique_id":"dnuPgbAhDSLQgmZQ8pwpX"}],"camera":false,"door_type":"single","default_state":true,"door_sound":"door_regular.ogg","items":[]},{"location_group":"La Puerta B","keep_open":false,"secret":false,"auto_lock":5,"door_name":"306","perms":{"ace":[],"passcode":"","identifier":[],"discord":[],"job":[{"name":"police","grade":0}],"items":[]},"unique_id":"KTKS-SHXS-DVZ8-G3H6","door_unlock_sound":"door_click.ogg","distance":2,"state":true,"lockpickable":false,"door_data":[{"pivot_coords":{"y":-1041.1383056640626,"z":65.97110748291016,"x":-450.5216674804688},"door_coords":{"y":-1041.1383056640626,"z":65.97115325927735,"x":-451.1717529296875},"model_hash":-1028247766,"unique_id":"TpP4GPXyR5x5FbRXBsVBf"}],"camera":false,"door_type":"single","default_state":true,"door_sound":"door_regular.ogg","items":[]},{"location_group":"La Puerta B","keep_open":false,"secret":false,"auto_lock":5,"door_name":"400","perms":{"ace":[],"passcode":"","identifier":[],"discord":[],"job":[{"name":"police","grade":0}],"items":[]},"unique_id":"KEKC-I9AE-DPRO-JZ4C","door_unlock_sound":"door_click.ogg","distance":2,"state":true,"lockpickable":false,"door_data":[{"pivot_coords":{"y":-1041.1383056640626,"z":76.97113037109375,"x":-492.375732421875},"door_coords":{"y":-1041.1383056640626,"z":76.97117614746094,"x":-493.02581787109377},"model_hash":-1028247766,"unique_id":"sUoDrudmF7W7ZyNJkEH41"}],"camera":false,"door_type":"single","default_state":true,"door_sound":"door_regular.ogg","items":[]},{"location_group":"La Puerta B","keep_open":false,"secret":false,"auto_lock":5,"door_name":"401","perms":{"ace":[],"passcode":"","identifier":[],"discord":[],"job":[{"name":"police","grade":0}],"items":[]},"unique_id":"W5JL-0JKZ-RLI6-7VD2","door_unlock_sound":"door_click.ogg","distance":2,"state":true,"lockpickable":false,"door_data":[{"pivot_coords":{"y":-1046.199462890625,"z":76.97113037109375,"x":-478.69244384765627},"door_coords":{"y":-1046.199462890625,"z":76.97117614746094,"x":-478.0423583984375},"model_hash":-1028247766,"unique_id":"paH8H98oIAA5kyGVHIbif"}],"camera":false,"door_type":"single","default_state":true,"door_sound":"door_regular.ogg","items":[]},{"location_group":"La Puerta B","keep_open":false,"secret":false,"auto_lock":5,"door_name":"402","perms":{"ace":[],"passcode":"","identifier":[],"discord":[],"job":[{"name":"police","grade":0}],"items":[]},"unique_id":"4ZCF-C6BV-RW39-I5QI","door_unlock_sound":"door_click.ogg","distance":2,"state":true,"lockpickable":false,"door_data":[{"pivot_coords":{"y":-1041.1383056640626,"z":76.97113037109375,"x":-478.3059692382813},"door_coords":{"y":-1041.1383056640626,"z":76.97117614746094,"x":-478.9560546875},"model_hash":-1028247766,"unique_id":"RLYD43ABTTfIDMjlLc5VD"}],"camera":false,"door_type":"single","default_state":true,"door_sound":"door_regular.ogg","items":[]},{"location_group":"La Puerta B","keep_open":false,"secret":false,"auto_lock":5,"door_name":"403","perms":{"ace":[],"passcode":"","identifier":[],"discord":[],"job":[{"name":"police","grade":0}],"items":[]},"unique_id":"A0BU-OTCM-E4VP-04BA","door_unlock_sound":"door_click.ogg","distance":2,"state":true,"lockpickable":false,"door_data":[{"pivot_coords":{"y":-1046.199462890625,"z":76.97113037109375,"x":-464.7496337890625},"door_coords":{"y":-1046.199462890625,"z":76.97117614746094,"x":-464.09954833984377},"model_hash":-1028247766,"unique_id":"bUE--D73cLqwQY66-n3-Y"}],"camera":false,"door_type":"single","default_state":true,"door_sound":"door_regular.ogg","items":[]},{"location_group":"La Puerta B","keep_open":false,"secret":false,"auto_lock":5,"door_name":"404","perms":{"ace":[],"passcode":"","identifier":[],"discord":[],"job":[{"name":"police","grade":0}],"items":[]},"unique_id":"W1X4-SQJG-UBNE-4IEI","door_unlock_sound":"door_click.ogg","distance":2,"state":true,"lockpickable":false,"door_data":[{"pivot_coords":{"y":-1041.1383056640626,"z":76.97113037109375,"x":-464.44775390625},"door_coords":{"y":-1041.1383056640626,"z":76.97117614746094,"x":-465.0978393554688},"model_hash":-1028247766,"unique_id":"dyj1u8O7GV0Y2nQ5CmLnc"}],"camera":false,"door_type":"single","default_state":true,"door_sound":"door_regular.ogg","items":[]},{"location_group":"La Puerta B","keep_open":false,"secret":false,"auto_lock":5,"door_name":"405","perms":{"ace":[],"passcode":"","identifier":[],"discord":[],"job":[{"name":"police","grade":0}],"items":[]},"unique_id":"GUIB-C7ES-A4H9-W8QD","door_unlock_sound":"door_click.ogg","distance":2,"state":true,"lockpickable":false,"door_data":[{"pivot_coords":{"y":-1046.199462890625,"z":76.97113037109375,"x":-450.83782958984377},"door_coords":{"y":-1046.199462890625,"z":76.97117614746094,"x":-450.187744140625},"model_hash":-1028247766,"unique_id":"4FBiZH5Kv6-Udj5hnSz0f"}],"camera":false,"door_type":"single","default_state":true,"door_sound":"door_regular.ogg","items":[]},{"location_group":"La Puerta B","keep_open":false,"secret":false,"auto_lock":5,"door_name":"406","perms":{"ace":[],"passcode":"","identifier":[],"discord":[],"job":[{"name":"police","grade":0}],"items":[]},"unique_id":"GJC5-IVWD-OTZA-4IT8","door_unlock_sound":"door_click.ogg","distance":2,"state":true,"lockpickable":false,"door_data":[{"pivot_coords":{"y":-1041.1383056640626,"z":76.97113037109375,"x":-450.5216674804688},"door_coords":{"y":-1041.1383056640626,"z":76.97117614746094,"x":-451.1717529296875},"model_hash":-1028247766,"unique_id":"MDZ6uV8lvcabTHjoUmrgC"}],"camera":false,"door_type":"single","default_state":true,"door_sound":"door_regular.ogg","items":[]},{"location_group":"La Puerta B","keep_open":false,"secret":false,"auto_lock":5,"door_name":"500","perms":{"ace":[],"passcode":"","identifier":[],"discord":[],"job":[{"name":"police","grade":0}],"items":[]},"unique_id":"RI38-SIDH-BKZH-3E7S","door_unlock_sound":"door_click.ogg","distance":2,"state":true,"lockpickable":false,"door_data":[{"pivot_coords":{"y":-1041.1383056640626,"z":87.97112274169922,"x":-492.375732421875},"door_coords":{"y":-1041.1383056640626,"z":87.9711685180664,"x":-493.02581787109377},"model_hash":-1028247766,"unique_id":"IV23rsxWjS7lfsI37NUJk"}],"camera":false,"door_type":"single","default_state":true,"door_sound":"door_regular.ogg","items":[]},{"location_group":"La Puerta B","keep_open":false,"secret":false,"auto_lock":5,"door_name":"501","perms":{"ace":[],"passcode":"","identifier":[],"discord":[],"job":[{"name":"police","grade":0}],"items":[]},"unique_id":"F7K6-G066-RPMD-P16M","door_unlock_sound":"door_click.ogg","distance":2,"state":true,"lockpickable":false,"door_data":[{"pivot_coords":{"y":-1046.199462890625,"z":87.97112274169922,"x":-478.69244384765627},"door_coords":{"y":-1046.199462890625,"z":87.9711685180664,"x":-478.0423583984375},"model_hash":-1028247766,"unique_id":"pYwjSwg1T8H7jAm5S4QiM"}],"camera":false,"door_type":"single","default_state":true,"door_sound":"door_regular.ogg","items":[]},{"location_group":"La Puerta B","keep_open":false,"secret":false,"auto_lock":5,"door_name":"502","perms":{"ace":[],"passcode":"","identifier":[],"discord":[],"job":[{"name":"police","grade":0}],"items":[]},"unique_id":"DCYU-UZC0-EAHG-K3PI","door_unlock_sound":"door_click.ogg","distance":2,"state":true,"lockpickable":false,"door_data":[{"pivot_coords":{"y":-1041.1383056640626,"z":87.97112274169922,"x":-478.3059692382813},"door_coords":{"y":-1041.1383056640626,"z":87.9711685180664,"x":-478.9560546875},"model_hash":-1028247766,"unique_id":"pFnxkId1_H-rxcbunqqnI"}],"camera":false,"door_type":"single","default_state":true,"door_sound":"door_regular.ogg","items":[]},{"location_group":"La Puerta B","keep_open":false,"secret":false,"auto_lock":5,"door_name":"503","perms":{"ace":[],"passcode":"","identifier":[],"discord":[],"job":[{"name":"police","grade":0}],"items":[]},"unique_id":"2VE7-QTB3-BVIF-AH6J","door_unlock_sound":"door_click.ogg","distance":2,"state":true,"lockpickable":false,"door_data":[{"pivot_coords":{"y":-1046.199462890625,"z":87.97112274169922,"x":-464.7496337890625},"door_coords":{"y":-1046.199462890625,"z":87.9711685180664,"x":-464.09954833984377},"model_hash":-1028247766,"unique_id":"o3-ba24xXJbFWbMNPFEhS"}],"camera":false,"door_type":"single","default_state":true,"door_sound":"door_regular.ogg","items":[]},{"location_group":"La Puerta B","keep_open":false,"secret":false,"auto_lock":5,"door_name":"504","perms":{"ace":[],"passcode":"","identifier":[],"discord":[],"job":[{"name":"police","grade":0}],"items":[]},"unique_id":"NEG5-AS6X-L98Y-ADAZ","door_unlock_sound":"door_click.ogg","distance":2,"state":true,"lockpickable":false,"door_data":[{"pivot_coords":{"y":-1041.1383056640626,"z":87.97112274169922,"x":-464.44775390625},"door_coords":{"y":-1041.1383056640626,"z":87.9711685180664,"x":-465.0978393554688},"model_hash":-1028247766,"unique_id":"zRN6Re_HE0tRUcO84eFre"}],"camera":false,"door_type":"single","default_state":true,"door_sound":"door_regular.ogg","items":[]},{"location_group":"La Puerta B","keep_open":false,"secret":false,"auto_lock":5,"door_name":"505","perms":{"ace":[],"passcode":"","identifier":[],"discord":[],"job":[{"name":"police","grade":0}],"items":[]},"unique_id":"KMUM-BXFI-5TFL-1KIX","door_unlock_sound":"door_click.ogg","distance":2,"state":true,"lockpickable":false,"door_data":[{"pivot_coords":{"y":-1046.199462890625,"z":87.97112274169922,"x":-450.83782958984377},"door_coords":{"y":-1046.199462890625,"z":87.9711685180664,"x":-450.187744140625},"model_hash":-1028247766,"unique_id":"qv-IbJgNtmcIo5KwIyJ8R"}],"camera":false,"door_type":"single","default_state":true,"door_sound":"door_regular.ogg","items":[]},{"location_group":"La Puerta B","keep_open":false,"secret":false,"auto_lock":5,"door_name":"506","perms":{"ace":[],"passcode":"","identifier":[],"discord":[],"job":[{"name":"police","grade":0}],"items":[]},"unique_id":"3IE0-ZSWB-AR9K-F6PM","door_unlock_sound":"door_click.ogg","distance":2,"state":true,"lockpickable":false,"door_data":[{"pivot_coords":{"y":-1041.1383056640626,"z":87.97112274169922,"x":-450.5216674804688},"door_coords":{"y":-1041.1383056640626,"z":87.9711685180664,"x":-451.1717529296875},"model_hash":-1028247766,"unique_id":"2kILCsEWub3MhNycId_Jy"}],"camera":false,"door_type":"single","default_state":true,"door_sound":"door_regular.ogg","items":[]},{"location_group":"La Puerta B","keep_open":false,"secret":false,"auto_lock":5,"door_name":"600","perms":{"ace":[],"passcode":"","identifier":[],"discord":[],"job":[{"name":"police","grade":0}],"items":[]},"unique_id":"62NV-BCWE-B2GI-9XSS","door_unlock_sound":"door_click.ogg","distance":2,"state":true,"lockpickable":false,"door_data":[{"pivot_coords":{"y":-1041.1383056640626,"z":98.97116088867188,"x":-492.375732421875},"door_coords":{"y":-1041.1383056640626,"z":98.97120666503906,"x":-493.02581787109377},"model_hash":-1028247766,"unique_id":"3DaUjGZjf_SYiCLH07DOY"}],"camera":false,"door_type":"single","default_state":true,"door_sound":"door_regular.ogg","items":[]},{"location_group":"La Puerta B","keep_open":false,"secret":false,"auto_lock":5,"door_name":"601","perms":{"ace":[],"passcode":"","identifier":[],"discord":[],"job":[{"name":"police","grade":0}],"items":[]},"unique_id":"BI9F-NKE4-YZIW-CL1D","door_unlock_sound":"door_click.ogg","distance":2,"state":true,"lockpickable":false,"door_data":[{"pivot_coords":{"y":-1046.199462890625,"z":98.97116088867188,"x":-478.69244384765627},"door_coords":{"y":-1046.199462890625,"z":98.97120666503906,"x":-478.0423583984375},"model_hash":-1028247766,"unique_id":"yH4iTI059BnlUd7eSzOFc"}],"camera":false,"door_type":"single","default_state":true,"door_sound":"door_regular.ogg","items":[]},{"location_group":"La Puerta B","keep_open":false,"secret":false,"auto_lock":5,"door_name":"602","perms":{"ace":[],"passcode":"","identifier":[],"discord":[],"job":[{"name":"police","grade":0}],"items":[]},"unique_id":"Y39Y-6M75-N76U-UX9T","door_unlock_sound":"door_click.ogg","distance":2,"state":true,"lockpickable":false,"door_data":[{"pivot_coords":{"y":-1041.1383056640626,"z":98.97116088867188,"x":-478.3059692382813},"door_coords":{"y":-1041.1383056640626,"z":98.97120666503906,"x":-478.9560546875},"model_hash":-1028247766,"unique_id":"xbT68gJ6rqQVOLc2kliZk"}],"camera":false,"door_type":"single","default_state":true,"door_sound":"door_regular.ogg","items":[]},{"location_group":"La Puerta B","keep_open":false,"secret":false,"auto_lock":5,"door_name":"603","perms":{"ace":[],"passcode":"","identifier":[],"discord":[],"job":[{"name":"police","grade":0}],"items":[]},"unique_id":"HM1N-18MA-XOTK-BORC","door_unlock_sound":"door_click.ogg","distance":2,"state":true,"lockpickable":false,"door_data":[{"pivot_coords":{"y":-1046.199462890625,"z":98.97116088867188,"x":-464.7496337890625},"door_coords":{"y":-1046.199462890625,"z":98.97120666503906,"x":-464.09954833984377},"model_hash":-1028247766,"unique_id":"sEQR23ga3Wa6u3KRnD9Qa"}],"camera":false,"door_type":"single","default_state":true,"door_sound":"door_regular.ogg","items":[]},{"location_group":"La Puerta B","keep_open":false,"secret":false,"auto_lock":5,"door_name":"604","perms":{"ace":[],"passcode":"","identifier":[],"discord":[],"job":[{"name":"police","grade":0}],"items":[]},"unique_id":"PD3J-N8C5-J2UI-CV5D","door_unlock_sound":"door_click.ogg","distance":2,"state":true,"lockpickable":false,"door_data":[{"pivot_coords":{"y":-1041.1383056640626,"z":98.97116088867188,"x":-464.44775390625},"door_coords":{"y":-1041.1383056640626,"z":98.97120666503906,"x":-465.0978393554688},"model_hash":-1028247766,"unique_id":"ybWUxRF3LzUcvtv28R5m3"}],"camera":false,"door_type":"single","default_state":true,"door_sound":"door_regular.ogg","items":[]},{"location_group":"La Puerta B","keep_open":false,"secret":false,"auto_lock":5,"door_name":"605","perms":{"ace":[],"passcode":"","identifier":[],"discord":[],"job":[{"name":"police","grade":0}],"items":[]},"unique_id":"926C-4Z1J-XJPW-1BEF","door_unlock_sound":"door_click.ogg","distance":2,"state":true,"lockpickable":false,"door_data":[{"pivot_coords":{"y":-1046.199462890625,"z":98.97116088867188,"x":-450.83782958984377},"door_coords":{"y":-1046.199462890625,"z":98.97120666503906,"x":-450.187744140625},"model_hash":-1028247766,"unique_id":"VLlXg4twufqYmv7kMubwY"}],"camera":false,"door_type":"single","default_state":true,"door_sound":"door_regular.ogg","items":[]},{"location_group":"La Puerta B","keep_open":false,"secret":false,"auto_lock":5,"door_name":"606","perms":{"ace":[],"passcode":"","identifier":[],"discord":[],"job":[{"name":"police","grade":0}],"items":[]},"unique_id":"TSIY-JE2E-C2RL-2LS8","door_unlock_sound":"door_click.ogg","distance":2,"state":true,"lockpickable":false,"door_data":[{"pivot_coords":{"y":-1041.1383056640626,"z":98.97116088867188,"x":-450.5216674804688},"door_coords":{"y":-1041.1383056640626,"z":98.97120666503906,"x":-451.1717529296875},"model_hash":-1028247766,"unique_id":"0-NxzImSpZZ2uaeyAfQdl"}],"camera":false,"door_type":"single","default_state":true,"door_sound":"door_regular.ogg","items":[]},{"location_group":"La Puerta B","keep_open":false,"secret":false,"auto_lock":5,"door_name":"700","perms":{"ace":[],"passcode":"","identifier":[],"discord":[],"job":[{"name":"police","grade":0}],"items":[]},"unique_id":"WZ3W-2MH1-71P2-8S04","door_unlock_sound":"door_click.ogg","distance":2,"state":true,"lockpickable":false,"door_data":[{"pivot_coords":{"y":-1041.1383056640626,"z":104.4711456298828,"x":-492.375732421875},"door_coords":{"y":-1041.1383056640626,"z":104.47119140625,"x":-493.02581787109377},"model_hash":-1028247766,"unique_id":"q7YApPpuusQ30SPgMeBrx"}],"camera":false,"door_type":"single","default_state":true,"door_sound":"door_regular.ogg","items":[]},{"location_group":"La Puerta B","keep_open":false,"secret":false,"auto_lock":5,"door_name":"701","perms":{"ace":[],"passcode":"","identifier":[],"discord":[],"job":[{"name":"police","grade":0}],"items":[]},"unique_id":"P5QZ-EZ21-F4DC-DU3A","door_unlock_sound":"door_click.ogg","distance":2,"state":true,"lockpickable":false,"door_data":[{"pivot_coords":{"y":-1046.199462890625,"z":104.4711456298828,"x":-478.69244384765627},"door_coords":{"y":-1046.199462890625,"z":104.47119140625,"x":-478.0423583984375},"model_hash":-1028247766,"unique_id":"q25xeyyiZjytJL9lJ6a5y"}],"camera":false,"door_type":"single","default_state":true,"door_sound":"door_regular.ogg","items":[]},{"location_group":"La Puerta B","keep_open":false,"secret":false,"auto_lock":5,"door_name":"702","perms":{"ace":[],"passcode":"","identifier":[],"discord":[],"job":[{"name":"police","grade":0}],"items":[]},"unique_id":"E6RO-G2AD-8INQ-QP3P","door_unlock_sound":"door_click.ogg","distance":2,"state":true,"lockpickable":false,"door_data":[{"pivot_coords":{"y":-1041.1383056640626,"z":104.4711456298828,"x":-478.3059692382813},"door_coords":{"y":-1041.1383056640626,"z":104.47119140625,"x":-478.9560546875},"model_hash":-1028247766,"unique_id":"SK6oIPemRh8upLHtvszV_"}],"camera":false,"door_type":"single","default_state":true,"door_sound":"door_regular.ogg","items":[]},{"location_group":"La Puerta B","keep_open":false,"secret":false,"auto_lock":5,"door_name":"703","perms":{"ace":[],"passcode":"","identifier":[],"discord":[],"job":[{"name":"police","grade":0}],"items":[]},"unique_id":"3HXB-VKKK-P7WH-IBBI","door_unlock_sound":"door_click.ogg","distance":2,"state":true,"lockpickable":false,"door_data":[{"pivot_coords":{"y":-1046.199462890625,"z":104.4711456298828,"x":-464.7496337890625},"door_coords":{"y":-1046.199462890625,"z":104.47119140625,"x":-464.09954833984377},"model_hash":-1028247766,"unique_id":"HH5FTfGPFup48qfSbj9w2"}],"camera":false,"door_type":"single","default_state":true,"door_sound":"door_regular.ogg","items":[]},{"location_group":"La Puerta B","keep_open":false,"secret":false,"auto_lock":5,"door_name":"704","perms":{"ace":[],"passcode":"","identifier":[],"discord":[],"job":[{"name":"police","grade":0}],"items":[]},"unique_id":"6P7B-O9XO-INGX-AOCV","door_unlock_sound":"door_click.ogg","distance":2,"state":true,"lockpickable":false,"door_data":[{"pivot_coords":{"y":-1041.1383056640626,"z":104.4711456298828,"x":-464.44775390625},"door_coords":{"y":-1041.1383056640626,"z":104.47119140625,"x":-465.0978393554688},"model_hash":-1028247766,"unique_id":"yPLwu3dCzfzwL6b_E4J7q"}],"camera":false,"door_type":"single","default_state":true,"door_sound":"door_regular.ogg","items":[]},{"location_group":"La Puerta B","keep_open":false,"secret":false,"auto_lock":5,"door_name":"705","perms":{"ace":[],"passcode":"","identifier":[],"discord":[],"job":[{"name":"police","grade":0}],"items":[]},"unique_id":"ELKS-JM2W-MFFJ-V882","door_unlock_sound":"door_click.ogg","distance":2,"state":true,"lockpickable":false,"door_data":[{"pivot_coords":{"y":-1046.199462890625,"z":104.4711456298828,"x":-450.83782958984377},"door_coords":{"y":-1046.199462890625,"z":104.47119140625,"x":-450.187744140625},"model_hash":-1028247766,"unique_id":"jN_nhAqlA608MsUJ2Jlpd"}],"camera":false,"door_type":"single","default_state":true,"door_sound":"door_regular.ogg","items":[]},{"location_group":"La Puerta B","keep_open":false,"secret":false,"auto_lock":5,"door_name":"706","perms":{"ace":[],"passcode":"","identifier":[],"discord":[],"job":[{"name":"police","grade":0}],"items":[]},"unique_id":"2O1G-LRVM-27HG-5Y28","door_unlock_sound":"door_click.ogg","distance":2,"state":true,"lockpickable":false,"door_data":[{"pivot_coords":{"y":-1041.1383056640626,"z":104.4711456298828,"x":-450.5216674804688},"door_coords":{"y":-1041.1383056640626,"z":104.47119140625,"x":-451.1717529296875},"model_hash":-1028247766,"unique_id":"b6X6lp6atRUe3sVwLZkwp"}],"camera":false,"door_type":"single","default_state":true,"door_sound":"door_regular.ogg","items":[]}],"imported":false}