{"data":[{"camera":false,"door_sound_unlock":"","door_type":"single","door_name":"Sandy Shores Motel G-1","location_group":"Sandy Motel","door_sound":"","state":true,"perms":{"identifier":[],"items":[],"job":[]},"secret":false,"unique_id":"KY5N-O0JC-O8QN-WMB5","door_data":[{"model_hash":718415028,"door_coords":{"z":35.05494689941406,"y":3787.65478515625,"x":1616.4639892578126},"unique_id":"0skCHJqGz13tg2kM1r9eV"}],"distance":2,"default_state":false,"keep_open":false},{"camera":false,"door_sound_unlock":"","door_type":"single","door_name":"Sandy Shores Motel G-2","location_group":"Sandy Motel","door_sound":"","state":true,"perms":{"identifier":[],"items":[],"job":[]},"secret":false,"unique_id":"QIA2-XWDR-YVLU-NLK0","door_data":[{"model_hash":718415028,"door_coords":{"z":35.05494689941406,"y":3784.28759765625,"x":1612.069091796875},"unique_id":"j7_nSfnj12p5y3v6Edk8k"}],"distance":2,"default_state":false,"keep_open":false},{"camera":false,"door_sound_unlock":"","door_type":"single","door_name":"Sandy Shores Motel G-3","location_group":"Sandy Motel","door_sound":"","state":true,"perms":{"identifier":[],"items":[],"job":[]},"secret":false,"unique_id":"GUOQ-H0T7-32X3-J0KS","door_data":[{"model_hash":718415028,"door_coords":{"z":35.05494689941406,"y":3780.892822265625,"x":1607.6707763671876},"unique_id":"-pEMBdg7TCXXEAwooM9gg"}],"distance":2,"default_state":false,"keep_open":false},{"camera":false,"door_sound_unlock":"","door_type":"single","door_name":"Sandy Shores Motel G-4","location_group":"Sandy Motel","door_sound":"","state":true,"perms":{"identifier":[],"items":[],"job":[]},"secret":false,"unique_id":"SLYJ-LHMB-WDEK-VDDQ","door_data":[{"model_hash":718415028,"door_coords":{"z":35.05494689941406,"y":3777.527587890625,"x":1603.28515625},"unique_id":"N9kWC2vEMd_b45TyX4fyI"}],"distance":2,"default_state":false,"keep_open":false},{"camera":false,"door_sound_unlock":"","door_type":"single","door_name":"Sandy Shores Motel G-5","location_group":"Sandy Motel","door_sound":"","state":true,"perms":{"identifier":[],"items":[],"job":[]},"secret":false,"unique_id":"117Q-NKL9-6DP3-5ERI","door_data":[{"model_hash":718415028,"door_coords":{"z":35.05878067016601,"y":3763.412353515625,"x":1584.8594970703126},"unique_id":"5sDobGpB7QcvinX4_s0G_"}],"distance":2,"default_state":false,"keep_open":false},{"camera":false,"door_sound_unlock":"","door_type":"single","door_name":"Sandy Shores Motel G-6","location_group":"Sandy Motel","door_sound":"","state":true,"perms":{"identifier":[],"items":[],"job":[]},"secret":false,"unique_id":"OWWL-FT3J-7HQV-K8OE","door_data":[{"model_hash":718415028,"door_coords":{"z":35.05878067016601,"y":3759.614501953125,"x":1579.904296875},"unique_id":"SbjWdTpxQDGq8IfKy1tKm"}],"distance":2,"default_state":false,"keep_open":false},{"camera":false,"door_sound_unlock":"","door_type":"single","door_name":"Sandy Shores Motel G-7","location_group":"Sandy Motel","door_sound":"","state":true,"perms":{"identifier":[],"items":[],"job":[]},"secret":false,"unique_id":"GI93-QKDM-NCPA-43WL","door_data":[{"model_hash":718415028,"door_coords":{"z":35.04315185546875,"y":3774.53125,"x":1623.28125},"unique_id":"-sRo2r9RQXbtsGPZh4LnY"}],"distance":2,"default_state":false,"keep_open":false},{"camera":false,"door_sound_unlock":"","door_type":"single","door_name":"Sandy Shores Motel G-8","location_group":"Sandy Motel","door_sound":"","state":true,"perms":{"identifier":[],"items":[],"job":[]},"secret":false,"unique_id":"12PI-I3XI-I3EN-S3PP","door_data":[{"model_hash":718415028,"door_coords":{"z":35.04315185546875,"y":3770.7275390625,"x":1618.3240966796876},"unique_id":"ycVeJ-pME15DOsAEcgoUS"}],"distance":2,"default_state":false,"keep_open":false},{"camera":false,"door_sound_unlock":"","door_type":"single","door_name":"Sandy Shores Motel G-9","location_group":"Sandy Motel","door_sound":"","state":true,"perms":{"identifier":[],"items":[],"job":[]},"secret":false,"unique_id":"UULG-88UM-6T5Z-6SJV","door_data":[{"model_hash":718415028,"door_coords":{"z":35.04315185546875,"y":3766.9091796875,"x":1613.3477783203126},"unique_id":"QpSjoL6JbBp58PLoj5Pu3"}],"distance":2,"default_state":false,"keep_open":false},{"camera":false,"door_sound_unlock":"","door_type":"single","door_name":"Sandy Shores Motel G-10","location_group":"Sandy Motel","door_sound":"","state":true,"perms":{"identifier":[],"items":[],"job":[]},"secret":false,"unique_id":"Z1NR-531T-PGHN-WS3B","door_data":[{"model_hash":718415028,"door_coords":{"z":35.04315185546875,"y":3763.091796875,"x":1608.3729248046876},"unique_id":"_FBMAP12TBm1G_J3CevPh"}],"distance":2,"default_state":false,"keep_open":false},{"camera":false,"door_sound_unlock":"","door_type":"single","door_name":"Sandy Shores Motel G-11","location_group":"Sandy Motel","door_sound":"","state":true,"perms":{"identifier":[],"items":[],"job":[]},"secret":false,"unique_id":"68S7-YXW5-K4XW-RI84","door_data":[{"model_hash":718415028,"door_coords":{"z":35.04315185546875,"y":3759.27734375,"x":1603.40185546875},"unique_id":"fNLDPTWZqV4KvFTlOiHKg"}],"distance":2,"default_state":false,"keep_open":false},{"camera":false,"door_sound_unlock":"","door_type":"single","door_name":"Sandy Shores Motel G-12","location_group":"Sandy Motel","door_sound":"","state":true,"perms":{"identifier":[],"items":[],"job":[]},"secret":false,"unique_id":"1BOR-5MJI-9L8Q-SYF2","door_data":[{"model_hash":718415028,"door_coords":{"z":35.04315185546875,"y":3755.456298828125,"x":1598.4222412109376},"unique_id":"hb2pGRrnGq5VqD9QgcJh0"}],"distance":2,"default_state":false,"keep_open":false},{"camera":false,"door_sound_unlock":"","door_type":"single","door_name":"Sandy Shores Motel G-13","location_group":"Sandy Motel","door_sound":"","state":true,"perms":{"identifier":[],"items":[],"job":[]},"secret":false,"unique_id":"GI69-W2W8-01OJ-7PQP","door_data":[{"model_hash":718415028,"door_coords":{"z":35.04315185546875,"y":3751.642822265625,"x":1593.4525146484376},"unique_id":"leB-PhHeCn48WFJvo7eEc"}],"distance":2,"default_state":false,"keep_open":false},{"camera":false,"door_sound_unlock":"","door_type":"single","door_name":"Sandy Shores Motel G-14","location_group":"Sandy Motel","door_sound":"","state":true,"perms":{"identifier":[],"items":[],"job":[]},"secret":false,"unique_id":"F9PN-NAZ7-FOCS-FC8D","door_data":[{"model_hash":718415028,"door_coords":{"z":35.04315185546875,"y":3748.107666015625,"x":1588.8453369140626},"unique_id":"OlkGGsY-Eep6c9x-OhSTO"}],"distance":2,"default_state":false,"keep_open":false},{"camera":false,"door_sound_unlock":"","door_type":"single","door_name":"Sandy Shores Motel G-15","location_group":"Sandy Motel","door_sound":"","state":true,"perms":{"identifier":[],"items":[],"job":[]},"secret":false,"unique_id":"ZBTY-PFDK-NCUF-66CB","door_data":[{"model_hash":718415028,"door_coords":{"z":35.04315185546875,"y":3744.637939453125,"x":1584.32421875},"unique_id":"AtMUAE9kN_dnj1K7MGyPF"}],"distance":2,"default_state":false,"keep_open":false},{"camera":false,"door_sound_unlock":"","door_type":"double","door_name":"Sandy Shores Motel G-16","location_group":"Sandy Motel","door_sound":"","state":true,"perms":{"identifier":[],"items":[],"job":[]},"secret":false,"unique_id":"TUCR-1PSZ-JR1J-8K2Q","door_data":[{"model_hash":-1087242187,"door_coords":{"z":35.13037109375,"y":3747.125244140625,"x":1577.6634521484376},"unique_id":"HOArJdYaEZAHQGgKxsVWK"},{"model_hash":-1087242187,"door_coords":{"z":35.13037109375,"y":3749.08837890625,"x":1576.1572265625},"unique_id":"4agHXvYBiwFhEQ5dUKttI"}],"distance":2,"default_state":false,"keep_open":false},{"camera":false,"door_sound_unlock":"","door_type":"single","door_name":"Sandy Shores Motel G-17","location_group":"Sandy Motel","door_sound":"","state":true,"perms":{"identifier":[],"items":[],"job":[]},"secret":false,"unique_id":"7AQ6-4H75-2UVE-LBJC","door_data":[{"model_hash":-2094971262,"door_coords":{"z":35.13277816772461,"y":3740.1240234375,"x":1573.8060302734376},"unique_id":"iPpedAXHo1_m0RjxF-RFe"}],"distance":2,"default_state":false,"keep_open":false},{"camera":false,"door_sound_unlock":"","door_type":"single","door_name":"Sandy Shores Motel 1-1","location_group":"Sandy Motel","door_sound":"","state":true,"perms":{"identifier":[],"items":[],"job":[]},"secret":false,"unique_id":"CJW7-CHKZ-18UL-DRNV","door_data":[{"model_hash":718415028,"door_coords":{"z":38.65202713012695,"y":3787.65478515625,"x":1616.4639892578126},"unique_id":"9xsG52__pw-FpFtX7WyC1"}],"distance":2,"default_state":false,"keep_open":false},{"camera":false,"door_sound_unlock":"","door_type":"single","door_name":"Sandy Shores Motel 1-2","location_group":"Sandy Motel","door_sound":"","state":true,"perms":{"identifier":[],"items":[],"job":[]},"secret":false,"unique_id":"7ZQF-22BB-FWGM-5CML","door_data":[{"model_hash":718415028,"door_coords":{"z":38.65202713012695,"y":3784.30712890625,"x":1612.09619140625},"unique_id":"j6g9lmL8AL37iTUXvuP_A"}],"distance":2,"default_state":false,"keep_open":false},{"camera":false,"door_sound_unlock":"","door_type":"single","door_name":"Sandy Shores Motel 1-3","location_group":"Sandy Motel","door_sound":"","state":true,"perms":{"identifier":[],"items":[],"job":[]},"secret":false,"unique_id":"G4U0-H8HX-0LQV-DQYB","door_data":[{"model_hash":718415028,"door_coords":{"z":38.65202713012695,"y":3780.92578125,"x":1607.700927734375},"unique_id":"I4FOonXYTgsbwwUAsSfvS"}],"distance":2,"default_state":false,"keep_open":false},{"camera":false,"door_sound_unlock":"","door_type":"single","door_name":"Sandy Shores Motel 1-4","location_group":"Sandy Motel","door_sound":"","state":true,"perms":{"identifier":[],"items":[],"job":[]},"secret":false,"unique_id":"LXXZ-GTQ6-WPPJ-BYII","door_data":[{"model_hash":718415028,"door_coords":{"z":38.65202713012695,"y":3777.501220703125,"x":1603.243408203125},"unique_id":"C_t4yf_oOsH-H-vS5JqOX"}],"distance":2,"default_state":false,"keep_open":false},{"camera":false,"door_sound_unlock":"","door_type":"single","door_name":"Sandy Shores Motel 1-5","location_group":"Sandy Motel","door_sound":"","state":true,"perms":{"identifier":[],"items":[],"job":[]},"secret":false,"unique_id":"H0UA-M00Z-UP8W-WF1E","door_data":[{"model_hash":718415028,"door_coords":{"z":38.65202713012695,"y":3761.370361328125,"x":1582.2303466796876},"unique_id":"Y7W9Ttda7T49q0OJY41TD"}],"distance":2,"default_state":false,"keep_open":false},{"camera":false,"door_sound_unlock":"","door_type":"single","door_name":"Sandy Shores Motel 1-6","location_group":"Sandy Motel","door_sound":"","state":true,"perms":{"identifier":[],"items":[],"job":[]},"secret":false,"unique_id":"5FAO-VWJG-LEHM-0828","door_data":[{"model_hash":718415028,"door_coords":{"z":38.65202713012695,"y":3757.58642578125,"x":1577.269775390625},"unique_id":"QFVa2hl23qjR_W41JCu_6"}],"distance":2,"default_state":false,"keep_open":false},{"camera":false,"door_sound_unlock":"","door_type":"single","door_name":"Sandy Shores Motel 1-7","location_group":"Sandy Motel","door_sound":"","state":true,"perms":{"identifier":[],"items":[],"job":[]},"secret":false,"unique_id":"GVN3-NN4G-5TG7-MOZI","door_data":[{"model_hash":718415028,"door_coords":{"z":38.65202713012695,"y":3753.769775390625,"x":1572.290283203125},"unique_id":"zix7OAvRw9Jn3du-WX1-T"}],"distance":2,"default_state":false,"keep_open":false},{"camera":false,"door_sound_unlock":"","door_type":"single","door_name":"Sandy Shores Motel 1-8","location_group":"Sandy Motel","door_sound":"","state":true,"perms":{"identifier":[],"items":[],"job":[]},"secret":false,"unique_id":"KMWW-34GV-YDL5-XYKU","door_data":[{"model_hash":718415028,"door_coords":{"z":38.65088653564453,"y":3774.52490234375,"x":1623.2734375},"unique_id":"fosLaZEXAKuKrlmXSA2el"}],"distance":2,"default_state":false,"keep_open":false},{"camera":false,"door_sound_unlock":"","door_type":"single","door_name":"Sandy Shores Motel 1-9","location_group":"Sandy Motel","door_sound":"","state":true,"perms":{"identifier":[],"items":[],"job":[]},"secret":false,"unique_id":"QL4V-1F9W-3Q7U-36OO","door_data":[{"model_hash":718415028,"door_coords":{"z":38.65088653564453,"y":3770.723388671875,"x":1618.3192138671876},"unique_id":"gsHG5wIJqY2S7Y_dgCz6q"}],"distance":2,"default_state":false,"keep_open":false},{"camera":false,"door_sound_unlock":"","door_type":"single","door_name":"Sandy Shores Motel 1-10","location_group":"Sandy Motel","door_sound":"","state":true,"perms":{"identifier":[],"items":[],"job":[]},"secret":false,"unique_id":"TM55-0BKM-I2NC-33FZ","door_data":[{"model_hash":718415028,"door_coords":{"z":38.65088653564453,"y":3766.914306640625,"x":1613.355224609375},"unique_id":"POkSQ1gPewCQedSL17a87"}],"distance":2,"default_state":false,"keep_open":false},{"camera":false,"door_sound_unlock":"","door_type":"single","door_name":"Sandy Shores Motel 1-11","location_group":"Sandy Motel","door_sound":"","state":true,"perms":{"identifier":[],"items":[],"job":[]},"secret":false,"unique_id":"BOXW-4PRD-6BGS-AZB0","door_data":[{"model_hash":718415028,"door_coords":{"z":38.65088653564453,"y":3763.10498046875,"x":1608.390625},"unique_id":"lL-0dKT-mJkc7539nK4rN"}],"distance":2,"default_state":false,"keep_open":false},{"camera":false,"door_sound_unlock":"","door_type":"single","door_name":"Sandy Shores Motel 1-12","location_group":"Sandy Motel","door_sound":"","state":true,"perms":{"identifier":[],"items":[],"job":[]},"secret":false,"unique_id":"5FN4-GG2Z-A7F3-XH5P","door_data":[{"model_hash":718415028,"door_coords":{"z":38.65088653564453,"y":3759.283447265625,"x":1603.4102783203126},"unique_id":"Je6B9perElFSKmPCnnL12"}],"distance":2,"default_state":false,"keep_open":false},{"camera":false,"door_sound_unlock":"","door_type":"single","door_name":"Sandy Shores Motel 1-13","location_group":"Sandy Motel","door_sound":"","state":true,"perms":{"identifier":[],"items":[],"job":[]},"secret":false,"unique_id":"O75G-OP1E-7EYY-4CM2","door_data":[{"model_hash":718415028,"door_coords":{"z":38.65088653564453,"y":3755.46044921875,"x":1598.4281005859376},"unique_id":"A6V-rF0x1JVCYtf1tU7SJ"}],"distance":2,"default_state":false,"keep_open":false},{"camera":false,"door_sound_unlock":"","door_type":"single","door_name":"Sandy Shores Motel 1-14","location_group":"Sandy Motel","door_sound":"","state":true,"perms":{"identifier":[],"items":[],"job":[]},"secret":false,"unique_id":"JM8G-4LF3-POO8-91PM","door_data":[{"model_hash":718415028,"door_coords":{"z":38.65088653564453,"y":3751.630859375,"x":1593.4371337890626},"unique_id":"LziRfjF5icK3Ibxlc0VlO"}],"distance":2,"default_state":false,"keep_open":false},{"camera":false,"door_sound_unlock":"","door_type":"single","door_name":"Sandy Shores Motel 1-15","location_group":"Sandy Motel","door_sound":"","state":true,"perms":{"identifier":[],"items":[],"job":[]},"secret":false,"unique_id":"THZB-UCGI-05KH-UKLK","door_data":[{"model_hash":718415028,"door_coords":{"z":38.65088653564453,"y":3747.822021484375,"x":1588.4732666015626},"unique_id":"l9w0KBSFiLaxxP-c5ecys"}],"distance":2,"default_state":false,"keep_open":false},{"camera":false,"door_sound_unlock":"","door_type":"single","door_name":"Sandy Shores Motel 1-16","location_group":"Sandy Motel","door_sound":"","state":true,"perms":{"identifier":[],"items":[],"job":[]},"secret":false,"unique_id":"H9PC-CKXJ-5W5O-U23K","door_data":[{"model_hash":718415028,"door_coords":{"z":38.6529655456543,"y":3744.00146484375,"x":1583.494384765625},"unique_id":"76mF47vhe2X9DcWyQ9N2R"}],"distance":2,"default_state":false,"keep_open":false},{"camera":false,"door_sound_unlock":"","door_type":"double","door_name":"Sandy Shores Motel 1-17","location_group":"Sandy Motel","door_sound":"","state":true,"perms":{"identifier":[],"items":[],"job":[]},"secret":false,"unique_id":"4SS6-C397-ET9O-HO9J","door_data":[{"model_hash":-1087242187,"door_coords":{"z":38.70522689819336,"y":3745.677001953125,"x":1575.7420654296876},"unique_id":"HRbdRYxnD-QQ_cWN7ttYt"},{"model_hash":-1087242187,"door_coords":{"z":38.70522689819336,"y":3747.640380859375,"x":1574.2257080078126},"unique_id":"hO-OU-ezbAC0Mc4V4cnOD"}],"distance":2,"default_state":false,"keep_open":false},{"camera":false,"door_sound_unlock":"","door_type":"single","door_name":"Sandy Shores Motel 1-18","location_group":"Sandy Motel","door_sound":"","state":true,"perms":{"identifier":[],"items":[],"job":[]},"secret":false,"unique_id":"3IG4-EIH8-2V7V-JFD2","door_data":[{"model_hash":-738528475,"door_coords":{"z":38.72258758544922,"y":3748.385498046875,"x":1571.0679931640626},"unique_id":"oxPZfOrutP5D_2n0jaETS"}],"distance":2,"default_state":false,"keep_open":false},{"camera":false,"door_sound_unlock":"","door_type":"single","door_name":"Sandy Shores Motel 1-19","location_group":"Sandy Motel","door_sound":"","state":true,"perms":{"identifier":[],"items":[],"job":[]},"secret":false,"unique_id":"LWLF-C4YO-QQOB-Y92V","door_data":[{"model_hash":-2094971262,"door_coords":{"z":38.75629806518555,"y":3742.169921875,"x":1575.3251953125},"unique_id":"g5egWYzCMiBr26VpHAlin"}],"distance":2,"default_state":false,"keep_open":false},{"camera":false,"door_sound_unlock":"","door_type":"single","door_name":"Sandy Shores Motel Secret-1","location_group":"Sandy Motel","door_sound":"","state":true,"perms":{"identifier":[],"items":[],"job":[]},"secret":true,"unique_id":"XQRI-1M6Y-X21I-ITTF","door_data":[{"model_hash":476235269,"door_coords":{"z":37.65934371948242,"y":3737.6748046875,"x":1578.78369140625},"unique_id":"O1NwNOMDFPke5VJvQDGhM"}],"distance":2,"default_state":false,"keep_open":false},{"camera":false,"door_sound_unlock":"","door_type":"single","door_name":"Sandy Shores Motel Secret-2","location_group":"Sandy Motel","door_sound":"","state":true,"perms":{"identifier":[],"items":[],"job":[]},"secret":true,"unique_id":"H6LU-Q5FV-BXQS-HQZJ","door_data":[{"model_hash":1358887135,"door_coords":{"z":37.66647338867187,"y":3750.52099609375,"x":1566.1815185546876},"unique_id":"Y5FBn1sWcDgQ1IhgUGij-"}],"distance":2,"default_state":false,"keep_open":false},{"camera":false,"door_sound_unlock":"","door_type":"single","door_name":"Sandy Shores Motel B-1","location_group":"Sandy Motel","door_sound":"","state":true,"perms":{"identifier":[],"items":[],"job":[]},"secret":false,"unique_id":"B28X-B5ZA-2PU8-AG69","door_data":[{"model_hash":-1259829481,"door_coords":{"z":31.5613784790039,"y":3740.513916015625,"x":1590.11328125},"unique_id":"tplJeRJbq2y7_OljMH6j_"}],"distance":2,"default_state":false,"keep_open":false},{"camera":false,"door_sound_unlock":"","door_type":"single","door_name":"Sandy Shores Motel B-2","location_group":"Sandy Motel","door_sound":"","state":false,"perms":{"identifier":[],"items":[],"job":[]},"secret":false,"unique_id":"6KZ3-X8HD-RNOA-TKP8","door_data":[{"model_hash":-1259829481,"door_coords":{"z":31.5802059173584,"y":3743.063720703125,"x":1593.438232421875},"unique_id":"IVkAy6DxU-zxJ2pfphDG5"}],"distance":2,"default_state":false,"keep_open":false}],"name":"[Prompt_Studio]_Sandy_Motel.json","imported":false}